{
"num_images": 6,
"name_image": "window",
"image_path": "./data/window/",
"output_dir": "./output/window/",
"out_01_drago_raw": "./output/window/01_drago_raw.png",
"out_02_drago_tonemap": "./output/window/02_drago_tonemap.png",
"out_03_drago_hist_equal": "./output/window/03_drago_hist_equal.png",
"out_04_drago_filtered": "./output/window/04_drago_filtered.png",
"out_01_reinhard_raw": "./output/window/01_reinhard_raw.png",
"out_02_reinhard_tonemap": "./output/window/02_reinhard_tonemap.png",
"out_03_reinhard_hist_equal": "./output/window/03_reinhard_hist_equal.png",
"out_04_reinhard_filtered": "./output/window/04_reinhard_filtered.png"
}

